rlabs_mini_gitlab/__init__.py
rlabs_mini_gitlab/api_kwargs.py
rlabs_mini_gitlab/checks.py
rlabs_mini_gitlab/common.py
rlabs_mini_gitlab/config.py
rlabs_mini_gitlab/directory.py
rlabs_mini_gitlab/error.py
rlabs_mini_gitlab/gitlab.py
rlabs_mini_gitlab/logger.py
rlabs_mini_gitlab/manual_test_run.py
rlabs_mini_gitlab/py.typed
rlabs_mini_gitlab/query_params.py
rlabs_mini_gitlab-2.0.5.dist-info/METADATA
rlabs_mini_gitlab-2.0.5.dist-info/WHEEL
rlabs_mini_gitlab-2.0.5.dist-info/entry_points.txt
rlabs_mini_gitlab-2.0.5.dist-info/RECORD
